monitor_air_quality/__init__.py
monitor_air_quality/monitor_air_quality.py
monitor_air_quality-2.0.2.dist-info/LICENSE
monitor_air_quality-2.0.2.dist-info/METADATA
monitor_air_quality-2.0.2.dist-info/WHEEL
monitor_air_quality-2.0.2.dist-info/entry_points.txt
monitor_air_quality-2.0.2.dist-info/top_level.txt
monitor_air_quality-2.0.2.dist-info/RECORD
