Metadata-Version: 2.1
Name: monitor-air-quality
Version: 2.0.2
Summary: Read data from sds011 sensor, gather purpleair and notion data and POST to an API
Home-page: https://github.com/gene1wood/monitor_air_quality
Author: Gene Wood
Author-email: gene_wood@cementhorizon.com
License: UNKNOWN
Platform: UNKNOWN
Requires-Python: >=3
License-File: LICENSE
Requires-Dist: PyYAML
Requires-Dist: requests
Requires-Dist: py-sds011
Requires-Dist: python-aqi
Requires-Dist: xdg
